{
	"configurations" : 
	[
		{
			"directories" : 
			[
				{
					"build" : ".",
					"jsonFile" : "directory-.-Debug-d0094a50bb2071803777.json",
					"minimumCMakeVersion" : 
					{
						"string" : "3.21"
					},
					"projectIndex" : 0,
					"source" : ".",
					"targetIndexes" : 
					[
						0
					]
				}
			],
			"name" : "Debug",
			"projects" : 
			[
				{
					"directoryIndexes" : 
					[
						0
					],
					"name" : "stack_i_permutacje",
					"targetIndexes" : 
					[
						0
					]
				}
			],
			"targets" : 
			[
				{
					"directoryIndex" : 0,
					"id" : "stack_i_permutacje::@6890427a1f51a3e7e1df",
					"jsonFile" : "target-stack_i_permutacje-Debug-eaa93c914230f0c10a3f.json",
					"name" : "stack_i_permutacje",
					"projectIndex" : 0
				}
			]
		}
	],
	"kind" : "codemodel",
	"paths" : 
	{
		"build" : "E:/Krzysztof/repozytoria/programowanie_imperatywne/stack_i_permutacje/cmake-build-debug",
		"source" : "E:/Krzysztof/repozytoria/programowanie_imperatywne/stack_i_permutacje"
	},
	"version" : 
	{
		"major" : 2,
		"minor" : 3
	}
}
